repraxis/__init__.py
repraxis/__version__.py
repraxis/database.py
repraxis/helpers.py
repraxis/py.typed
repraxis/nodes/__init__.py
repraxis/nodes/base_types.py
repraxis/nodes/nodes.py
repraxis/query/__init__.py
repraxis/query/base_types.py
repraxis/query/db_query.py
repraxis/query/expressions.py
repraxis/query/helpers.py
repraxis/query/query_binding_context.py
repraxis/query/query_result.py
repraxis/query/query_state.py
repraxis-1.3.1.dist-info/LICENSE.md
repraxis-1.3.1.dist-info/METADATA
repraxis-1.3.1.dist-info/WHEEL
repraxis-1.3.1.dist-info/top_level.txt
repraxis-1.3.1.dist-info/RECORD
