Metadata-Version: 2.1
Name: repraxis
Version: 1.3.1
Summary: An in-memory logic database solution for games, based on Versu's Praxis language.
Author-email: Shi Johnson-Bey <shijbey@gmail.com>
License: # MIT LICENSE
Project-URL: Homepage, https://github.com/ShiJbey/RePraxisPy
Project-URL: Documentation, https://github.com/ShiJbey/RePraxisPy/blob/main/README.md
Project-URL: Repository, https://github.com/ShiJbey/RePraxisPy.git
Project-URL: Issues, https://github.com/ShiJbey/RePraxisPy/issues
Project-URL: Changelog, https://github.com/ShiJbey/RePraxisPy/blob/main/CHANGELOG.md
Keywords: database,logic programming,praxis,versu,exclusion logic,games
Classifier: Intended Audience :: Developers
Classifier: Intended Audience :: Science/Research
Classifier: License :: OSI Approved :: MIT License
Classifier: Operating System :: OS Independent
Classifier: Programming Language :: Python :: 3 :: Only
Classifier: Programming Language :: Python :: 3.9
Classifier: Programming Language :: Python :: 3.10
Classifier: Programming Language :: Python :: 3.11
Classifier: Programming Language :: Python :: 3.12
Classifier: Topic :: Games/Entertainment :: Simulation
Classifier: Topic :: Sociology
Classifier: Topic :: Software Development :: Libraries
Classifier: Typing :: Typed
Requires-Python: >=3.9
License-File: LICENSE.md
Provides-Extra: development
Requires-Dist: isort ; extra == 'development'
Requires-Dist: black ; extra == 'development'
Requires-Dist: black[d] ; extra == 'development'
Requires-Dist: build ; extra == 'development'
Requires-Dist: pytest ; extra == 'development'
Requires-Dist: pytest-cov ; extra == 'development'
